urbamt/__init__.py
urbamt/translator.py
urbamt/utils/__init__.py
urbamt/utils/misc.py
urbamt/utils/tree_manipulation.py
urbamt-0.0.1b4.dist-info/LICENSE
urbamt-0.0.1b4.dist-info/METADATA
urbamt-0.0.1b4.dist-info/WHEEL
urbamt-0.0.1b4.dist-info/top_level.txt
urbamt-0.0.1b4.dist-info/RECORD
